{"metadata":{"result_type":"recent","iso_language_code":"es"},"in_reply_to_status_id_str":null,"in_reply_to_status_id":null,"created_at":"Mon Apr 09 00:53:04 +0000 2018","in_reply_to_user_id_str":null,"source":"<a href=\"http://www.botize.com\" rel=\"nofollow\">Botize<\/a>","retweet_count":0,"retweeted":false,"geo":null,"in_reply_to_screen_name":null,"is_quote_status":false,"id_str":"983145739034427393","in_reply_to_user_id":null,"favorite_count":0,"id":983145739034427393,"text":"La extensas grietas de África que alarman a la comunidad científica ¿Se divide el continente? #Alerta https://t.co/tHk6KdzbW4","place":null,"lang":"es","favorited":false,"possibly_sensitive":false,"coordinates":null,"truncated":false,"entities":{"urls":[{"display_url":"grandesmedios.com/alarma-cientif\u2026","indices":[102,125],"expanded_url":"https://www.grandesmedios.com/alarma-cientifica-grietas-de-africa/?btz56=0053040509","url":"https://t.co/tHk6KdzbW4"}],"hashtags":[{"indices":[94,101],"text":"Alerta"}],"user_mentions":[],"symbols":[]},"contributors":null,"user":{"utc_offset":-18000,"friends_count":56752,"profile_image_url_https":"https://pbs.twimg.com/profile_images/926792016700116994/WGzjHM71_normal.jpg","listed_count":701,"profile_background_image_url":"http://abs.twimg.com/images/themes/theme15/bg.png","default_profile_image":false,"favourites_count":5551,"description":"Emprendedora, Asesora de Contenidos en Medios de Comunicación.","created_at":"Wed May 21 04:56:08 +0000 2014","is_translator":false,"profile_background_image_url_https":"https://abs.twimg.com/images/themes/theme15/bg.png","protected":false,"screen_name":"DianaEinar","id_str":"2556959553","profile_link_color":"005494","is_translation_enabled":false,"translator_type":"none","id":2556959553,"geo_enabled":false,"profile_background_color":"000000","lang":"es","has_extended_profile":false,"profile_sidebar_border_color":"000000","profile_text_color":"000000","verified":false,"profile_image_url":"http://pbs.twimg.com/profile_images/926792016700116994/WGzjHM71_normal.jpg","time_zone":"Bogota","url":"https://t.co/3w8cw6u0Ch","contributors_enabled":false,"profile_background_tile":false,"profile_banner_url":"https://pbs.twimg.com/profile_banners/2556959553/1509799435","entities":{"description":{"urls":[]},"url":{"urls":[{"display_url":"grandesmedios.com","indices":[0,23],"expanded_url":"https://www.grandesmedios.com","url":"https://t.co/3w8cw6u0Ch"}]}},"statuses_count":1054494,"follow_request_sent":false,"followers_count":94123,"profile_use_background_image":false,"default_profile":false,"following":false,"name":"Diana Einar 🇪🇸","location":"Sevilla, España","profile_sidebar_fill_color":"000000","notifications":false}}