{"metadata":{"result_type":"recent","iso_language_code":"es"},"in_reply_to_status_id_str":null,"in_reply_to_status_id":null,"created_at":"Mon Apr 02 02:10:31 +0000 2018","in_reply_to_user_id_str":null,"source":"<a href=\"https://curiouscat.me\" rel=\"nofollow\">Curious Cat<\/a>","retweet_count":0,"retweeted":false,"geo":null,"in_reply_to_screen_name":null,"is_quote_status":false,"id_str":"980628511840002048","in_reply_to_user_id":null,"favorite_count":0,"id":980628511840002048,"text":"Holi https://t.co/miEerVno0b","place":null,"lang":"es","favorited":false,"possibly_sensitive":false,"coordinates":null,"truncated":false,"entities":{"urls":[{"display_url":"curiouscat.me/Chimchimblue","indices":[5,28],"expanded_url":"https://curiouscat.me/Chimchimblue","url":"https://t.co/miEerVno0b"}],"hashtags":[],"user_mentions":[],"symbols":[]},"contributors":null,"user":{"utc_offset":null,"friends_count":203,"profile_image_url_https":"https://pbs.twimg.com/profile_images/972658666087337985/7aO_SoId_normal.jpg","listed_count":1,"profile_background_image_url":null,"default_profile_image":false,"favourites_count":25378,"description":"excuse me","created_at":"Fri Oct 14 04:35:03 +0000 2016","is_translator":false,"profile_background_image_url_https":null,"protected":false,"screen_name":"Karla_Bustos_02","id_str":"786787377679216640","profile_link_color":"1DA1F2","is_translation_enabled":false,"translator_type":"none","id":786787377679216640,"geo_enabled":false,"profile_background_color":"F5F8FA","lang":"es","has_extended_profile":true,"profile_sidebar_border_color":"C0DEED","profile_text_color":"333333","verified":false,"profile_image_url":"http://pbs.twimg.com/profile_images/972658666087337985/7aO_SoId_normal.jpg","time_zone":null,"url":"https://t.co/sV9tiOdVcF","contributors_enabled":false,"profile_background_tile":false,"profile_banner_url":"https://pbs.twimg.com/profile_banners/786787377679216640/1520648365","entities":{"description":{"urls":[]},"url":{"urls":[{"display_url":"curiouscat.me/Chimchimblue","indices":[0,23],"expanded_url":"https://curiouscat.me/Chimchimblue","url":"https://t.co/sV9tiOdVcF"}]}},"statuses_count":10401,"follow_request_sent":false,"followers_count":202,"profile_use_background_image":true,"default_profile":true,"following":false,"name":"Ventress","location":"Argentina","profile_sidebar_fill_color":"DDEEF6","notifications":false}}