{"metadata":{"result_type":"recent","iso_language_code":"fr"},"in_reply_to_status_id_str":null,"in_reply_to_status_id":null,"created_at":"Fri Mar 02 13:40:05 +0000 2018","in_reply_to_user_id_str":null,"source":"<a href=\"http://twitter.com\" rel=\"nofollow\">Twitter Web Client<\/a>","retweet_count":1,"retweeted":false,"geo":null,"in_reply_to_screen_name":null,"is_quote_status":false,"id_str":"969568024943448065","in_reply_to_user_id":null,"favorite_count":1,"id":969568024943448065,"text":"Note de veille \u201cCRISPR, le gène à l\u2019ère du sur-mesure\u201d by @bertinalexandre  d'@UNITEC_Bdx  https://t.co/Vy4Nkx1huY","place":null,"lang":"fr","favorited":false,"possibly_sensitive":false,"coordinates":null,"truncated":false,"entities":{"urls":[{"display_url":"medium.com/@bertin.alexan\u2026","indices":[91,114],"expanded_url":"https://medium.com/@bertin.alexandre2010/crispr-le-g%C3%A8ne-%C3%A0-l%C3%A8re-du-sur-mesure-140ad2a2a3c8","url":"https://t.co/Vy4Nkx1huY"}],"hashtags":[],"user_mentions":[{"indices":[58,74],"screen_name":"bertinalexandre","id_str":"241101960","name":"Alexandre Bertin","id":241101960},{"indices":[78,89],"screen_name":"UNITEC_Bdx","id_str":"2204854916","name":"UNITEC","id":2204854916}],"symbols":[]},"contributors":null,"user":{"utc_offset":3600,"friends_count":913,"profile_image_url_https":"https://pbs.twimg.com/profile_images/555043267402690560/9LcRTPOh_normal.jpeg","listed_count":238,"profile_background_image_url":"http://pbs.twimg.com/profile_background_images/638839421/s3l71zp6pqt2tk2n3zg0.png","default_profile_image":false,"favourites_count":2925,"description":"Dir Com & Veille à @UNITEC_Bdx - Maitre de conf associé à @UBMontaigne #citenumerique #blockchain #opendata #videogame #etourisme #ecommerce #TedX #GenY #SerieZ","created_at":"Wed Jun 04 12:27:04 +0000 2008","is_translator":false,"profile_background_image_url_https":"https://pbs.twimg.com/profile_background_images/638839421/s3l71zp6pqt2tk2n3zg0.png","protected":false,"screen_name":"lpg","id_str":"15004246","profile_link_color":"0084B4","is_translation_enabled":false,"translator_type":"none","id":15004246,"geo_enabled":true,"profile_background_color":"FFFFFF","lang":"fr","has_extended_profile":true,"profile_sidebar_border_color":"C0DEED","profile_text_color":"333333","verified":false,"profile_image_url":"http://pbs.twimg.com/profile_images/555043267402690560/9LcRTPOh_normal.jpeg","time_zone":"Amsterdam","url":"https://t.co/3qGggpRyYw","contributors_enabled":false,"profile_background_tile":false,"profile_banner_url":"https://pbs.twimg.com/profile_banners/15004246/1398451096","entities":{"description":{"urls":[]},"url":{"urls":[{"display_url":"about.me/lpg","indices":[0,23],"expanded_url":"http://about.me/lpg","url":"https://t.co/3qGggpRyYw"}]}},"statuses_count":5693,"follow_request_sent":false,"followers_count":3751,"profile_use_background_image":true,"default_profile":false,"following":false,"name":"LP Gilliard","location":"Bordeaux","profile_sidebar_fill_color":"DDEEF6","notifications":false}}