{"metadata":{"result_type":"recent","iso_language_code":"en"},"in_reply_to_status_id_str":null,"in_reply_to_status_id":null,"coordinates":null,"created_at":"Sun Mar 04 05:03:18 +0000 2018","truncated":false,"in_reply_to_user_id_str":"2582637362","source":"<a href=\"http://twitter.com/download/iphone\" rel=\"nofollow\">Twitter for iPhone<\/a>","retweet_count":0,"retweeted":false,"geo":null,"in_reply_to_screen_name":"horikoshiko","is_quote_status":false,"entities":{"urls":[],"hashtags":[],"user_mentions":[{"indices":[0,12],"screen_name":"horikoshiko","id_str":"2582637362","name":"堀越耕平","id":2582637362}],"symbols":[]},"id_str":"970162746649030657","in_reply_to_user_id":2582637362,"favorite_count":0,"id":970162746649030657,"text":"@horikoshiko weekly updates of heroaca make me very very happy thank you for doing what you do sensei","place":null,"contributors":null,"lang":"en","user":{"utc_offset":28800,"friends_count":398,"profile_image_url_https":"https://pbs.twimg.com/profile_images/955066655410802690/DGMHOcSG_normal.jpg","listed_count":4,"profile_background_image_url":"http://pbs.twimg.com/profile_background_images/662191153173757952/iE5BXJ0y.png","default_profile_image":false,"favourites_count":14627,"description":"sometimes i do translations ☆华语/日本語 OK☆ bsd, hq, bnha | まふまふ、坂田、Neru、DECO*27 | love live, maimai | shoma, yuzuru, evgenia, misha, vincent","created_at":"Sun May 26 12:14:41 +0000 2013","is_translator":false,"profile_background_image_url_https":"https://pbs.twimg.com/profile_background_images/662191153173757952/iE5BXJ0y.png","protected":false,"screen_name":"dostoyevskykun","id_str":"1459478046","profile_link_color":"FF691F","is_translation_enabled":false,"translator_type":"regular","id":1459478046,"geo_enabled":false,"profile_background_color":"FA743E","lang":"en","has_extended_profile":false,"profile_sidebar_border_color":"000000","profile_text_color":"362720","verified":false,"profile_image_url":"http://pbs.twimg.com/profile_images/955066655410802690/DGMHOcSG_normal.jpg","time_zone":"Singapore","url":"https://t.co/LRJX0JUDDk","contributors_enabled":false,"profile_background_tile":true,"profile_banner_url":"https://pbs.twimg.com/profile_banners/1459478046/1474458619","entities":{"description":{"urls":[]},"url":{"urls":[{"display_url":"twitter.com/dostoyevskykun\u2026","indices":[0,23],"expanded_url":"https://twitter.com/dostoyevskykun/status/947839675812548609","url":"https://t.co/LRJX0JUDDk"}]}},"statuses_count":32653,"follow_request_sent":false,"followers_count":427,"profile_use_background_image":true,"default_profile":false,"following":false,"name":"c @ (not in hero) academia hell","location":"❝ remember that we lived ❞","profile_sidebar_fill_color":"E5507E","notifications":false},"favorited":false}